nflbdb/__init__.py
nflbdb/extract.py
nflbdb/transform.py
nflbdb/viz.py
nflbdb-2022.310.2.dist-info/WHEEL
nflbdb-2022.310.2.dist-info/METADATA
nflbdb-2022.310.2.dist-info/RECORD
