Metadata-Version: 2.1
Name: nflbdb
Version: 2022.310.2
Summary: My utilities for work with Big Data Bowl Datasets
Author-email: Brock Tibert <btibert3@gmail.com>
Requires-Python: >=3.7.12
Requires-Dist: pandas
Requires-Dist: imageio
Requires-Dist: seaborn
Project-URL: Home, https://github.com/Btibert3/nflbdb
